MANIFEST.in
README.md
build.py
pyproject.toml
requirements-dev.txt
requirements.txt
setup.py
test.py
auto_meshroom/__init__.py
auto_meshroom/__main__.py
auto_meshroom/base.py
auto_meshroom/commands.py
auto_meshroom/exceptions.py
auto_meshroom/io.py
auto_meshroom/mesh.py
auto_meshroom/modeling.py
auto_meshroom.egg-info/PKG-INFO
auto_meshroom.egg-info/SOURCES.txt
auto_meshroom.egg-info/dependency_links.txt
auto_meshroom.egg-info/requires.txt
auto_meshroom.egg-info/top_level.txt
auto_meshroom/source/assets/icon/icon.ico
auto_meshroom/source/assets/icon/icon.png